cnr/__init__.py
cnr/calls.yaml
cnr/exception.py
cnr/pacakge.json
cnr/packager.py
cnr/semver.py
cnr/utils.py
cnr/api/__init__.py
cnr/api/app.py
cnr/api/config.py
cnr/api/info.py
cnr/api/registry.py
cnr/api/wsgi.py
cnr/api/impl/__init__.py
cnr/api/impl/registry.py
cnr/models/__init__.py
cnr/models/blob_base.py
cnr/models/channel_base.py
cnr/models/db_base.py
cnr/models/package_base.py
cnr/models/kv/__init__.py
cnr/models/kv/blob_kv_base.py
cnr/models/kv/channel_kv_base.py
cnr/models/kv/models_index_base.py
cnr/models/kv/package_kv_base.py
cnr/models/kv/etcd/__init__.py
cnr/models/kv/etcd/blob.py
cnr/models/kv/etcd/channel.py
cnr/models/kv/etcd/db.py
cnr/models/kv/etcd/models_index.py
cnr/models/kv/etcd/package.py
cnr/models/kv/filesystem/__init__.py
cnr/models/kv/filesystem/blob.py
cnr/models/kv/filesystem/channel.py
cnr/models/kv/filesystem/db.py
cnr/models/kv/filesystem/models_index.py
cnr/models/kv/filesystem/package.py
cnr/models/kv/redis/__init__.py
cnr/models/kv/redis/blob.py
cnr/models/kv/redis/channel.py
cnr/models/kv/redis/db.py
cnr/models/kv/redis/models_index.py
cnr/models/kv/redis/package.py
cnr/tests/__init__.py
cnr/tests/conftest.py
cnr/tests/test_apiserver.py
cnr/tests/test_models.py
cnr/tests/data/backup1.json
cnr/tests/data/backup2.json
cnr/tests/data/kube-ui.tar.gz
cnr/tests/data/kube-ui_release.json
cnr/tests/data/manifest.yaml
cnr/tests/data/thirdparty.yaml
cnr/tests/data/bad_manifest/manifest.yaml
cnr/tests/data/docker-compose/manifest.jsonnet
cnr/tests/data/docker-compose/templates/compose-wordpress.yaml
cnr/tests/data/kube-ui/README.md
cnr/tests/data/kube-ui/file_to_ignore.yaml
cnr/tests/data/kube-ui/manifest.yaml
cnr/tests/data/kube-ui/templates/another_file_to_ignore.cfg
cnr/tests/data/kube-ui/templates/kube-ui-rc.yaml
cnr/tests/data/kube-ui/templates/kube-ui-svc.yaml
cnr/tests/data/responses/kube-ui-replicationcontroller.json
cnr/tests/data/responses/kube-ui-service.json
cnr_server-0.2.7.post2.dist-info/DESCRIPTION.rst
cnr_server-0.2.7.post2.dist-info/METADATA
cnr_server-0.2.7.post2.dist-info/RECORD
cnr_server-0.2.7.post2.dist-info/WHEEL
cnr_server-0.2.7.post2.dist-info/dependency_links.txt
cnr_server-0.2.7.post2.dist-info/metadata.json
cnr_server-0.2.7.post2.dist-info/top_level.txt
